NDATools/AltEndpointSSLAdapter.py
NDATools/Configuration.py
NDATools/Download.py
NDATools/Utils.py
NDATools/__init__.py
NDATools/clientscripts/__init__.py
NDATools/clientscripts/downloadcmd.py
NDATools/clientscripts/nda.py
NDATools/clientscripts/vtcmd.py
NDATools/clientscripts/config/logging.yml
NDATools/clientscripts/config/settings.cfg
NDATools/upload/__init__.py
NDATools/upload/batch_file_uploader.py
NDATools/upload/cli.py
NDATools/upload/submission/__init__.py
NDATools/upload/submission/api.py
NDATools/upload/submission/associated_file.py
NDATools/upload/submission/resubmission.py
NDATools/upload/validation/__init__.py
NDATools/upload/validation/api.py
NDATools/upload/validation/manifests.py
NDATools/upload/validation/results_writer.py
NDATools/upload/validation/v1.py
nda_tools-0.6.0.data/data/config/logging.yml
nda_tools-0.6.0.data/data/config/settings.cfg
nda_tools-0.6.0.dist-info/licenses/LICENSE.md
tests/__init__.py
tests/conftest.py
tests/test_authentication.py
tests/test_download.py
tests/test_utils.py
tests/test_validation.py
tests/clientscripts/__init__.py
tests/clientscripts/test_validate.py
tests/clientscripts/test_vtcmd.py
tests/upload/__init__.py
tests/upload/conftest.py
tests/upload/test_cli.py
tests/upload/submission/__init__.py
tests/upload/submission/conftest.py
tests/upload/submission/test_api.py
tests/upload/submission/test_associated_file.py
tests/upload/submission/test_resubmission.py
tests/upload/validation/__init__.py
tests/upload/validation/test_api.py
tests/upload/validation/test_manifests.py
tests/upload/validation/test_resultswriter.py
nda_tools-0.6.0.dist-info/METADATA
nda_tools-0.6.0.dist-info/WHEEL
nda_tools-0.6.0.dist-info/entry_points.txt
nda_tools-0.6.0.dist-info/top_level.txt
nda_tools-0.6.0.dist-info/RECORD
