Metadata-Version: 2.4
Name: nda_tools
Version: 0.6.0
Summary: NIMH Data Archive Python Client
Home-page: https://github.com/NDAR/nda-tools/tree/master/NDATools
Author: NDA
Author-email: NDAHelp@mail.nih.gov
License: MIT
License-File: LICENSE.md
Requires-Dist: boto3>=1.36.18
Requires-Dist: tqdm
Requires-Dist: requests
Requires-Dist: packaging
Requires-Dist: pyyaml
Requires-Dist: keyring
Requires-Dist: pandas
Requires-Dist: s3transfer
Requires-Dist: tabulate
Requires-Dist: pydantic>=2
Requires-Dist: setuptools
Provides-Extra: test
Requires-Dist: pytest; extra == "test"
Requires-Dist: pytest-datadir; extra == "test"
Requires-Dist: mock; extra == "test"
Requires-Dist: coverage; extra == "test"
Dynamic: author
Dynamic: author-email
Dynamic: description
Dynamic: description-content-type
Dynamic: home-page
Dynamic: license
Dynamic: license-file
Dynamic: provides-extra
Dynamic: requires-dist
Dynamic: summary
